canmatrix/__init__.py
canmatrix/_version.py
canmatrix/cancluster.py
canmatrix/canmatrix.py
canmatrix/compare.py
canmatrix/convert.py
canmatrix/copy.py
canmatrix/j1939.dbc
canmatrix/j1939_decoder.py
canmatrix/join.py
canmatrix/log.py
canmatrix/types.py
canmatrix/utils.py
canmatrix/cli/__init__.py
canmatrix/cli/compare.py
canmatrix/cli/convert.py
canmatrix/formats/__init__.py
canmatrix/formats/arxml.py
canmatrix/formats/csv.py
canmatrix/formats/dbc.py
canmatrix/formats/dbf.py
canmatrix/formats/fibex.py
canmatrix/formats/json.py
canmatrix/formats/kcd.py
canmatrix/formats/ldf.py
canmatrix/formats/odx.py
canmatrix/formats/scapy.py
canmatrix/formats/sym.py
canmatrix/formats/wireshark.py
canmatrix/formats/xls.py
canmatrix/formats/xls_common.py
canmatrix/formats/xlsx.py
canmatrix/formats/yaml.py
canmatrix/tests/ARXMLCompuMethod1.arxml
canmatrix/tests/ARXMLContainerTest.arxml
canmatrix/tests/ARXMLSecuredPDUTest.arxml
canmatrix/tests/ARXML_min_max.arxml
canmatrix/tests/MyECU.ecuc.arxml
canmatrix/tests/__init__.py
canmatrix/tests/aa.dbc
canmatrix/tests/asdf_aa.dbc
canmatrix/tests/test_arxml.py
canmatrix/tests/test_arxml_gw.py
canmatrix/tests/test_canmatrix.py
canmatrix/tests/test_cli_compare.py
canmatrix/tests/test_cli_convert.py
canmatrix/tests/test_copy.py
canmatrix/tests/test_dbc.py
canmatrix/tests/test_dbf.py
canmatrix/tests/test_formats.py
canmatrix/tests/test_frame_decoding.dbc
canmatrix/tests/test_frame_decoding.py
canmatrix/tests/test_frame_encoding.py
canmatrix/tests/test_j1939_decoder.py
canmatrix/tests/test_json.py
canmatrix/tests/test_scapy.py
canmatrix/tests/test_sym.py
canmatrix/tests/test_utils.py
canmatrix/tests/test_wireshark.py
canmatrix/tests/test_xls.py
canmatrix/tests/tmp.dbc
canmatrix/tests/tmpa.dbc
canmatrix/tests/tmpb.dbc
canmatrix-1.0.dist-info/LICENSE
canmatrix-1.0.dist-info/METADATA
canmatrix-1.0.dist-info/WHEEL
canmatrix-1.0.dist-info/entry_points.txt
canmatrix-1.0.dist-info/top_level.txt
canmatrix-1.0.dist-info/RECORD
