Metadata-Version: 2.1
Name: canmatrix
Version: 1.0
Summary: UNKNOWN
Home-page: http://github.com/ebroecker/canmatrix
Maintainer: Eduard Broecker
Maintainer-email: eduard@gmx.de
License: BSD
Keywords: CAN dbc arxml kcd dbf sym
Platform: any
Classifier: Development Status :: 4 - Beta
Classifier: Environment :: Console
Classifier: License :: OSI Approved :: BSD License
Classifier: Topic :: Scientific/Engineering
Classifier: Programming Language :: Python
Classifier: Programming Language :: Python :: 2.7
Classifier: Programming Language :: Python :: 3.4
Classifier: Programming Language :: Python :: 3.5
Classifier: Programming Language :: Python :: 3.6
Classifier: Programming Language :: Python :: 3.7
Classifier: Programming Language :: Python :: 3.8
Classifier: Programming Language :: Python :: 3.9
Classifier: Programming Language :: Python :: 3.10
Classifier: Programming Language :: Python :: 3.11
Provides-Extra: arxml
Provides-Extra: csv
Provides-Extra: dbc
Provides-Extra: dbf
Provides-Extra: fibex
Provides-Extra: json
Provides-Extra: kcd
Provides-Extra: ldf
Provides-Extra: odx
Provides-Extra: scapy
Provides-Extra: sym
Provides-Extra: test
Provides-Extra: wireshark
Provides-Extra: xls
Provides-Extra: xlsx
Provides-Extra: yaml
License-File: LICENSE
